tksamc/__init__.py
tksamc/cli.py
tksamc/solver.py
tksamc-1.0.1.dist-info/licenses/LICENSE
tksamc-1.0.1.dist-info/METADATA
tksamc-1.0.1.dist-info/WHEEL
tksamc-1.0.1.dist-info/entry_points.txt
tksamc-1.0.1.dist-info/top_level.txt
tksamc-1.0.1.dist-info/RECORD
