Metadata-Version: 2.4
Name: tksamc
Version: 1.0.1
Summary: TKSA - Electrostatic Free Energy calculation for each ionizable residue
Author: Vinícius G. Contessoto
Project-URL: Homepage, https://github.com/contessoto/tksamc
Classifier: Programming Language :: Python :: 3
Classifier: License :: OSI Approved :: MIT License
Classifier: Operating System :: OS Independent
Classifier: Topic :: Scientific/Engineering :: Bio-Informatics
Classifier: Topic :: Scientific/Engineering :: Chemistry
Requires-Python: >=3.6
License-File: LICENSE
Requires-Dist: numpy
Requires-Dist: scipy
Requires-Dist: matplotlib
Requires-Dist: mdtraj
Requires-Dist: numba
Dynamic: license-file
